[
  {
    "action": "update_item",
    "payload": {
      "id": 21,
      "before": {
        "id": 21,
        "title": "Стирка",
        "text": "Стирка",
        "details": "",
        "day": "пятница",
        "time": "16:00",
        "priority": "medium",
        "tags": [],
        "recurring": null,
        "reminder_offsets": [
          30,
          10
        ],
        "done": false,
        "created_at": "2026-04-17T03:06:36"
      }
    },
    "created_at": "2026-04-17T16:42:28"
  },
  {
    "action": "update_item",
    "payload": {
      "id": 18,
      "before": {
        "id": 18,
        "title": "Работа по ecopfr.ru",
        "text": "Работа по ecopfr.ru",
        "details": "",
        "day": "пятница",
        "time": "11:00",
        "priority": "medium",
        "tags": [
          "работа"
        ],
        "recurring": null,
        "reminder_offsets": [
          60,
          30,
          10
        ],
        "done": false,
        "created_at": "2026-04-16T17:25:10"
      }
    },
    "created_at": "2026-04-17T21:15:38"
  },
  {
    "action": "update_item",
    "payload": {
      "id": 19,
      "before": {
        "id": 19,
        "title": "Тренировка",
        "text": "Тренировка",
        "details": "Ноги",
        "day": "пятница",
        "time": "19:00",
        "priority": "high",
        "tags": [
          "тренировка"
        ],
        "recurring": null,
        "reminder_offsets": [
          60,
          30,
          10
        ],
        "done": false,
        "created_at": "2026-04-16T22:22:34"
      }
    },
    "created_at": "2026-04-17T21:15:57"
  },
  {
    "action": "add",
    "payload": {
      "created_ids": [
        25
      ]
    },
    "created_at": "2026-04-18T11:31:43"
  },
  {
    "action": "update_item",
    "payload": {
      "id": 25,
      "before": {
        "id": 25,
        "title": "Работа по Stylish-house.com",
        "text": "Работа по Stylish-house.com",
        "details": "",
        "due_date": "2026-04-18",
        "day": "суббота",
        "time": "20:10",
        "priority": "high",
        "tags": [
          "работа"
        ],
        "status": "active",
        "done": false,
        "done_at": null,
        "created_at": "2026-04-18T11:31:43",
        "updated_at": null,
        "reminder_offsets": [
          60,
          30,
          10
        ],
        "series_id": null,
        "recurrence_rule": null,
        "generated_from_rule": false,
        "legacy_day": "суббота"
      }
    },
    "created_at": "2026-04-18T12:22:18"
  },
  {
    "action": "update_item",
    "payload": {
      "id": 25,
      "before": {
        "id": 25,
        "title": "Работа по Stylish-house.com",
        "text": "Работа по Stylish-house.com",
        "details": "",
        "due_date": "2026-04-19",
        "day": "воскресенье",
        "time": "20:10",
        "priority": "high",
        "tags": [
          "работа"
        ],
        "status": "active",
        "done": false,
        "done_at": null,
        "created_at": "2026-04-18T11:31:43",
        "updated_at": "2026-04-18T12:22:18",
        "reminder_offsets": [
          60,
          30,
          10
        ],
        "series_id": null,
        "recurrence_rule": null,
        "generated_from_rule": false,
        "legacy_day": "воскресенье"
      }
    },
    "created_at": "2026-04-18T12:25:56"
  },
  {
    "action": "update_item",
    "payload": {
      "id": 23,
      "before": {
        "id": 23,
        "title": "врач у миши",
        "text": "врач у миши",
        "details": "",
        "due_date": "2026-04-21",
        "day": "вторник",
        "time": "09:20",
        "priority": "high",
        "tags": [
          "здоровье"
        ],
        "status": "active",
        "done": false,
        "done_at": null,
        "created_at": "2026-04-17T15:17:50",
        "updated_at": null,
        "reminder_offsets": [
          600,
          60,
          30
        ],
        "series_id": null,
        "recurrence_rule": null,
        "generated_from_rule": false,
        "legacy_day": "вторник"
      }
    },
    "created_at": "2026-04-18T12:32:16"
  },
  {
    "action": "add",
    "payload": {
      "created_ids": [
        26
      ]
    },
    "created_at": "2026-04-18T12:33:05"
  },
  {
    "action": "restore_items",
    "payload": {
      "items": [
        {
          "id": 26,
          "title": "Врач у Миши",
          "text": "Врач у Миши",
          "details": "",
          "due_date": "2026-04-21",
          "day": "вторник",
          "time": "09:20",
          "priority": "high",
          "tags": [
            "здоровье"
          ],
          "status": "active",
          "done": false,
          "done_at": null,
          "created_at": "2026-04-18T12:33:05",
          "updated_at": null,
          "reminder_offsets": [
            600,
            60,
            30
          ],
          "series_id": null,
          "recurrence_rule": null,
          "generated_from_rule": false,
          "legacy_day": "вторник"
        }
      ]
    },
    "created_at": "2026-04-18T12:33:10"
  },
  {
    "action": "restore_items",
    "payload": {
      "items": [
        {
          "id": 24,
          "title": "прпоп",
          "text": "прпоп",
          "details": "",
          "due_date": "2026-04-20",
          "day": "понедельник",
          "time": "22:30",
          "priority": "medium",
          "tags": [],
          "status": "active",
          "done": false,
          "done_at": null,
          "created_at": "2026-04-17T15:24:07",
          "updated_at": null,
          "reminder_offsets": [
            60,
            30,
            10
          ],
          "series_id": null,
          "recurrence_rule": null,
          "generated_from_rule": false,
          "legacy_day": "понедельник"
        }
      ]
    },
    "created_at": "2026-04-18T12:33:22"
  },
  {
    "action": "update_item",
    "payload": {
      "id": 20,
      "before": {
        "id": 20,
        "title": "пастирать крысам",
        "text": "пастирать крысам",
        "details": "",
        "due_date": "2026-04-24",
        "day": "пятница",
        "time": "22:00",
        "priority": "high",
        "tags": [
          "домашние дела"
        ],
        "status": "active",
        "done": false,
        "done_at": null,
        "created_at": "2026-04-16T22:30:53",
        "updated_at": null,
        "reminder_offsets": [
          60,
          30,
          10
        ],
        "series_id": null,
        "recurrence_rule": null,
        "generated_from_rule": false,
        "legacy_day": "пятница"
      }
    },
    "created_at": "2026-04-18T12:34:16"
  },
  {
    "action": "add",
    "payload": {
      "created_ids": [
        26
      ]
    },
    "created_at": "2026-04-18T17:08:44"
  },
  {
    "action": "restore_items",
    "payload": {
      "items": [
        {
          "id": 18,
          "title": "Работа по ecopfr.ru",
          "text": "Работа по ecopfr.ru",
          "details": "",
          "due_date": "2026-04-24",
          "day": "пятница",
          "time": "11:00",
          "priority": "medium",
          "tags": [
            "работа"
          ],
          "status": "done",
          "done": true,
          "done_at": "2026-04-17T21:15:38",
          "created_at": "2026-04-16T17:25:10",
          "updated_at": null,
          "reminder_offsets": [
            60,
            30,
            10
          ],
          "series_id": null,
          "recurrence_rule": null,
          "generated_from_rule": false,
          "legacy_day": "пятница"
        }
      ]
    },
    "created_at": "2026-04-18T17:09:43"
  },
  {
    "action": "restore_items",
    "payload": {
      "items": [
        {
          "id": 21,
          "title": "Стирка",
          "text": "Стирка",
          "details": "",
          "due_date": "2026-04-24",
          "day": "пятница",
          "time": "17:00",
          "priority": "medium",
          "tags": [],
          "status": "done",
          "done": true,
          "done_at": "2026-04-17T16:49:33",
          "created_at": "2026-04-17T03:06:36",
          "updated_at": null,
          "reminder_offsets": [
            17,
            10
          ],
          "series_id": null,
          "recurrence_rule": null,
          "generated_from_rule": false,
          "legacy_day": "пятница"
        }
      ]
    },
    "created_at": "2026-04-18T17:09:48"
  },
  {
    "action": "restore_items",
    "payload": {
      "items": [
        {
          "id": 22,
          "title": "Работа по stylish",
          "text": "Работа по stylish",
          "details": "шаблоны + расчеты",
          "due_date": "2026-04-24",
          "day": "пятница",
          "time": "13:00",
          "priority": "medium",
          "tags": [
            "работа"
          ],
          "status": "active",
          "done": false,
          "done_at": null,
          "created_at": "2026-04-17T03:15:14",
          "updated_at": null,
          "reminder_offsets": [
            60,
            30,
            10
          ],
          "series_id": null,
          "recurrence_rule": null,
          "generated_from_rule": false,
          "legacy_day": "пятница"
        }
      ]
    },
    "created_at": "2026-04-18T17:09:57"
  },
  {
    "action": "add",
    "payload": {
      "created_ids": [
        26
      ]
    },
    "created_at": "2026-04-18T17:13:17"
  },
  {
    "action": "restore_items",
    "payload": {
      "items": [
        {
          "id": 19,
          "title": "Тренировка",
          "text": "Тренировка",
          "details": "Ноги",
          "due_date": "2026-04-18",
          "day": "суббота",
          "time": "19:00",
          "priority": "high",
          "tags": [
            "тренировка"
          ],
          "status": "active",
          "done": false,
          "done_at": null,
          "created_at": "2026-04-16T22:22:34",
          "updated_at": null,
          "reminder_offsets": [
            60,
            30,
            10
          ],
          "series_id": null,
          "recurrence_rule": null,
          "generated_from_rule": false,
          "legacy_day": "суббота"
        }
      ]
    },
    "created_at": "2026-04-19T05:53:14"
  },
  {
    "action": "update_item",
    "payload": {
      "id": 25,
      "before": {
        "id": 25,
        "title": "Работа по Stylish-house.com",
        "text": "Работа по Stylish-house.com",
        "details": "",
        "due_date": "2026-04-18",
        "day": "суббота",
        "time": "20:10",
        "priority": "high",
        "tags": [
          "работа"
        ],
        "status": "active",
        "done": false,
        "done_at": null,
        "created_at": "2026-04-18T11:31:43",
        "updated_at": "2026-04-18T12:25:56",
        "reminder_offsets": [
          60,
          30,
          10
        ],
        "series_id": null,
        "recurrence_rule": null,
        "generated_from_rule": false,
        "legacy_day": "суббота"
      }
    },
    "created_at": "2026-04-19T05:53:29"
  },
  {
    "action": "update_item",
    "payload": {
      "id": 20,
      "before": {
        "id": 20,
        "title": "Дошить гамак",
        "text": "Дошить гамак",
        "details": "",
        "due_date": "2026-04-18",
        "day": "суббота",
        "time": "14:00",
        "priority": "high",
        "tags": [
          "домашние дела"
        ],
        "status": "active",
        "done": false,
        "done_at": null,
        "created_at": "2026-04-16T22:30:53",
        "updated_at": "2026-04-18T12:34:16",
        "reminder_offsets": [
          60,
          30,
          10
        ],
        "series_id": null,
        "recurrence_rule": null,
        "generated_from_rule": false,
        "legacy_day": "суббота"
      }
    },
    "created_at": "2026-04-19T05:53:41"
  },
  {
    "action": "update_item",
    "payload": {
      "id": 20,
      "before": {
        "id": 20,
        "title": "Дошить гамак",
        "text": "Дошить гамак",
        "details": "",
        "due_date": "2026-04-20",
        "day": "понедельник",
        "time": "14:00",
        "priority": "high",
        "tags": [
          "домашние дела"
        ],
        "status": "active",
        "done": false,
        "done_at": null,
        "created_at": "2026-04-16T22:30:53",
        "updated_at": "2026-04-19T05:53:41",
        "reminder_offsets": [
          60,
          30,
          10
        ],
        "series_id": null,
        "recurrence_rule": null,
        "generated_from_rule": false,
        "legacy_day": "понедельник"
      }
    },
    "created_at": "2026-04-19T05:54:05"
  },
  {
    "action": "update_item",
    "payload": {
      "id": 25,
      "before": {
        "id": 25,
        "title": "Работа по Stylish-house.com",
        "text": "Работа по Stylish-house.com",
        "details": "",
        "due_date": "2026-04-20",
        "day": "понедельник",
        "time": "20:10",
        "priority": "high",
        "tags": [
          "работа"
        ],
        "status": "active",
        "done": false,
        "done_at": null,
        "created_at": "2026-04-18T11:31:43",
        "updated_at": "2026-04-19T05:53:29",
        "reminder_offsets": [
          60,
          30,
          10
        ],
        "series_id": null,
        "recurrence_rule": null,
        "generated_from_rule": false,
        "legacy_day": "понедельник"
      }
    },
    "created_at": "2026-04-19T05:54:15"
  },
  {
    "action": "update_item",
    "payload": {
      "id": 25,
      "before": {
        "id": 25,
        "title": "Работа по Stylish-house.com",
        "text": "Работа по Stylish-house.com",
        "details": "",
        "due_date": "2026-04-19",
        "day": "воскресенье",
        "time": "20:10",
        "priority": "high",
        "tags": [
          "работа"
        ],
        "status": "active",
        "done": false,
        "done_at": null,
        "created_at": "2026-04-18T11:31:43",
        "updated_at": "2026-04-19T05:54:15",
        "reminder_offsets": [
          60,
          30,
          10
        ],
        "series_id": null,
        "recurrence_rule": null,
        "generated_from_rule": false,
        "legacy_day": "воскресенье"
      }
    },
    "created_at": "2026-04-19T05:54:23"
  },
  {
    "action": "add",
    "payload": {
      "created_ids": [
        27
      ]
    },
    "created_at": "2026-04-19T13:10:58"
  },
  {
    "action": "update_item",
    "payload": {
      "id": 27,
      "before": {
        "id": 27,
        "title": "Stylish-house.net",
        "text": "Stylish-house.net",
        "details": "Доработать модуль с рачетами",
        "due_date": "2026-04-19",
        "day": "воскресенье",
        "time": "12:00",
        "priority": "medium",
        "tags": [
          "работа"
        ],
        "status": "active",
        "done": false,
        "done_at": null,
        "created_at": "2026-04-19T13:10:58",
        "updated_at": null,
        "reminder_offsets": [
          60,
          30,
          10
        ],
        "series_id": null,
        "recurrence_rule": null,
        "generated_from_rule": false,
        "legacy_day": "воскресенье"
      }
    },
    "created_at": "2026-04-19T13:11:26"
  },
  {
    "action": "add",
    "payload": {
      "created_ids": [
        28
      ]
    },
    "created_at": "2026-04-19T13:12:43"
  },
  {
    "action": "add",
    "payload": {
      "created_ids": [
        29
      ]
    },
    "created_at": "2026-04-19T13:13:34"
  },
  {
    "action": "update_item",
    "payload": {
      "id": 29,
      "before": {
        "id": 29,
        "title": "Стирка",
        "text": "Стирка",
        "details": "для зала",
        "due_date": "2026-04-20",
        "day": "понедельник",
        "time": "10:00",
        "priority": "medium",
        "tags": [],
        "status": "active",
        "done": false,
        "done_at": null,
        "created_at": "2026-04-19T13:13:34",
        "updated_at": null,
        "reminder_offsets": [
          60,
          30,
          10
        ],
        "series_id": null,
        "recurrence_rule": null,
        "generated_from_rule": false,
        "legacy_day": "понедельник"
      }
    },
    "created_at": "2026-04-19T19:17:47"
  },
  {
    "action": "update_item",
    "payload": {
      "id": 17,
      "before": {
        "id": 17,
        "title": "Тренировка",
        "text": "Тренировка",
        "details": "СУПЕРТРЕНЯ!!!!",
        "due_date": "2026-04-19",
        "day": "воскресенье",
        "time": "15:00",
        "priority": "high",
        "tags": [
          "тренировка"
        ],
        "status": "active",
        "done": false,
        "done_at": null,
        "created_at": "2026-04-16T14:50:17",
        "updated_at": null,
        "reminder_offsets": [
          120,
          60,
          30,
          10
        ],
        "series_id": null,
        "recurrence_rule": null,
        "generated_from_rule": false,
        "legacy_day": "воскресенье"
      }
    },
    "created_at": "2026-04-19T19:18:19"
  },
  {
    "action": "update_item",
    "payload": {
      "id": 20,
      "before": {
        "id": 20,
        "title": "Дошить гамак",
        "text": "Дошить гамак",
        "details": "",
        "due_date": "2026-04-19",
        "day": "воскресенье",
        "time": "14:00",
        "priority": "high",
        "tags": [
          "домашние дела"
        ],
        "status": "active",
        "done": false,
        "done_at": null,
        "created_at": "2026-04-16T22:30:53",
        "updated_at": "2026-04-19T05:54:05",
        "reminder_offsets": [
          60,
          30,
          10
        ],
        "series_id": null,
        "recurrence_rule": null,
        "generated_from_rule": false,
        "legacy_day": "воскресенье"
      }
    },
    "created_at": "2026-04-19T23:53:15"
  },
  {
    "action": "add",
    "payload": {
      "created_ids": [
        30
      ]
    },
    "created_at": "2026-04-20T11:48:31"
  }
]